trial4/__init__.py
trial4/trail4_second_assignment.py
trial4/trial4.py
trial4-0.3.0.dist-info/LICENSE
trial4-0.3.0.dist-info/METADATA
trial4-0.3.0.dist-info/WHEEL
trial4-0.3.0.dist-info/top_level.txt
trial4-0.3.0.dist-info/RECORD
